{
	"model": "5205",
	"cmdSchema": [
		{
			"cmd_id": 18,
			"id": 1,
			"name": "Mic Gain",
			"options": [
				{
					"id": "busCh",
					"label": "Channel",
					"type": "dropdown",
					"choices": [
						{ "id": 0, "label": "Channel 1" },
						{ "id": 1, "label": "Channel 2" }
					],
					"default": 0,
					"tooltip": "Select the Mic Channel"
				},
				{
					"id": "value",
					"label": "Gain",
					"type": "dropdown",
					"choices": [
						{ "id": 0, "label": "0 dB" },
						{ "id": 20, "label": "20 dB" },
						{ "id": 30, "label": "30 dB" },
						{ "id": 40, "label": "40 dB" },
						{ "id": 50, "label": "50 dB" },
						{ "id": 60, "label": "60 dB" }
					],
					"default": 0,
					"tooltip": "Set the microphone preamplifier gain for the selected channel"
				}
			]
		},
		{
			"cmd_id": 18,
			"id": 2,
			"name": "Mic Phantom Power",
			"options": [
				{
					"id": "busCh",
					"label": "Channel",
					"type": "dropdown",
					"choices": [
						{ "id": 0, "label": "Channel 1" },
						{ "id": 1, "label": "Channel 2" }
					],
					"default": 0,
					"tooltip": "Set the Mic Channel"
				},
				{
					"id": "value",
					"label": "Phantom (+48v)",
					"type": "dropdown",
					"choices": [
						{ "id": 0, "label": "Off" },
						{ "id": 48, "label": "On" }
					],
					"default": 0,
					"tooltip": "Set phantom power for the selected channel"
				}
			]
		}
	]
}
